waghamdb/__init__.py
waghamdb/exceptions.py
waghamdb/pipelines.py
waghamdb-0.0.3.dist-info/LICENSE
waghamdb-0.0.3.dist-info/METADATA
waghamdb-0.0.3.dist-info/WHEEL
waghamdb-0.0.3.dist-info/top_level.txt
waghamdb-0.0.3.dist-info/RECORD
