Metadata-Version: 2.1
Name: waghamdb
Version: 0.0.3
Summary: MongoDB Python interface for all the Wagham-related projects
Author-email: Vincenzo Claudio Pierro <v.c.pierro@gmail.com>
License: Copyright 2022        
Project-URL: Homepage, https://github.com/TestaDiRapa/wagham-db
Project-URL: Bug Tracker, https://github.com/TestaDiRapa/wagham-db/issues
Classifier: Programming Language :: Python :: 3
Classifier: License :: OSI Approved :: MIT License
Classifier: Operating System :: OS Independent
Requires-Python: >=3.7
License-File: LICENSE
